layout2svg/__init__.py
layout2svg/cli.py
layout2svg/data.py
layout2svg/layout2svg.py
layout2svg-0.1.6.dist-info/entry_points.txt
layout2svg-0.1.6.dist-info/LICENSE
layout2svg-0.1.6.dist-info/WHEEL
layout2svg-0.1.6.dist-info/METADATA
layout2svg-0.1.6.dist-info/RECORD
